delegatefn/__init__.py
delegatefn/py.typed
delegatefn/test_delegate.py
delegatefn-0.4.2.dist-info/LICENSE
delegatefn-0.4.2.dist-info/WHEEL
delegatefn-0.4.2.dist-info/METADATA
delegatefn-0.4.2.dist-info/RECORD
