Metadata-Version: 2.1
Name: delegatefn
Version: 0.4.2
Summary: Signature-preserving function delegation
Author: IsaacBreen
Author-email: 57783927+IsaacBreen@users.noreply.github.com
Requires-Python: >=3.9,<4.0
Classifier: Programming Language :: Python :: 3
Classifier: Programming Language :: Python :: 3.9
Classifier: Programming Language :: Python :: 3.10
Classifier: Programming Language :: Python :: 3.11
